jax_am/__init__.py
jax_am/common.py
jax_am/cfd/__init__.py
jax_am/cfd/cfd_am.py
jax_am/cfd/gamma.py
jax_am/fem/__init__.py
jax_am/fem/basis.py
jax_am/fem/core.py
jax_am/fem/generate_mesh.py
jax_am/fem/mma.py
jax_am/fem/models.py
jax_am/fem/solver.py
jax_am/fem/utils.py
jax_am/phase_field/__init__.py
jax_am/phase_field/allen_cahn.py
jax_am/phase_field/neper.py
jax_am/phase_field/utils.py
jax_am/phase_field/yaml_parser.py
jax_am-0.0.3.dist-info/LICENSE
jax_am-0.0.3.dist-info/METADATA
jax_am-0.0.3.dist-info/WHEEL
jax_am-0.0.3.dist-info/top_level.txt
jax_am-0.0.3.dist-info/RECORD
