Metadata-Version: 2.1
Name: jax-am
Version: 0.0.3
Summary: GPU-accelerated simulation toolbox for additive manufacturing based on JAX.
Home-page: https://github.com/tianjuxue/jax-am
Author: Xue et al.
Author-email: tianjuxue@outlook.com
License: GPL-3.0
Classifier: Programming Language :: Python :: 3
Classifier: Operating System :: MacOS
Classifier: Operating System :: POSIX :: Linux
Classifier: Topic :: Software Development
Classifier: Topic :: Scientific/Engineering
Classifier: Intended Audience :: Science/Research
Requires-Python: >=3.6
License-File: LICENSE
Requires-Dist: jax
Requires-Dist: jaxlib
Requires-Dist: matplotlib
Requires-Dist: numpy
Requires-Dist: scipy
Requires-Dist: orix
Requires-Dist: meshio
Requires-Dist: gmsh
Requires-Dist: pyfiglet
Requires-Dist: scikit-learn
Requires-Dist: fenics-basix
